vygdb/__init__.py
vygdb/gdb_client.py
vygdb/server.py
vygdb/main/main.html
vygdb/main/main.js
vygdb/main/wsinit.js
vygdb-2.1.0.dist-info/METADATA
vygdb-2.1.0.dist-info/WHEEL
vygdb-2.1.0.dist-info/entry_points.txt
vygdb-2.1.0.dist-info/top_level.txt
vygdb-2.1.0.dist-info/RECORD
